odoo/addons/base_view_inheritance_extension/README.rst
odoo/addons/base_view_inheritance_extension/__init__.py
odoo/addons/base_view_inheritance_extension/__manifest__.py
odoo/addons/base_view_inheritance_extension/demo/ir_ui_view.xml
odoo/addons/base_view_inheritance_extension/i18n/base_view_inheritance_extension.pot
odoo/addons/base_view_inheritance_extension/i18n/ca.po
odoo/addons/base_view_inheritance_extension/i18n/de.po
odoo/addons/base_view_inheritance_extension/i18n/es.po
odoo/addons/base_view_inheritance_extension/i18n/hr.po
odoo/addons/base_view_inheritance_extension/i18n/it.po
odoo/addons/base_view_inheritance_extension/i18n/sl.po
odoo/addons/base_view_inheritance_extension/i18n/tr.po
odoo/addons/base_view_inheritance_extension/models/__init__.py
odoo/addons/base_view_inheritance_extension/models/ir_ui_view.py
odoo/addons/base_view_inheritance_extension/readme/CONTRIBUTORS.rst
odoo/addons/base_view_inheritance_extension/readme/DESCRIPTION.rst
odoo/addons/base_view_inheritance_extension/readme/ROADMAP.rst
odoo/addons/base_view_inheritance_extension/readme/USAGE.rst
odoo/addons/base_view_inheritance_extension/static/description/icon.png
odoo/addons/base_view_inheritance_extension/static/description/index.html
odoo/addons/base_view_inheritance_extension/tests/__init__.py
odoo/addons/base_view_inheritance_extension/tests/test_base_view_inheritance_extension.py
odoo14_addon_base_view_inheritance_extension-14.0.2.0.1.dist-info/METADATA
odoo14_addon_base_view_inheritance_extension-14.0.2.0.1.dist-info/WHEEL
odoo14_addon_base_view_inheritance_extension-14.0.2.0.1.dist-info/top_level.txt
odoo14_addon_base_view_inheritance_extension-14.0.2.0.1.dist-info/RECORD
